xrp_price_aggregate/__init__.py
xrp_price_aggregate/__main__.py
xrp_price_aggregate/aggregate_filter.py
xrp_price_aggregate/py.typed
xrp_price_aggregate/providers/__init__.py
xrp_price_aggregate/providers/base.py
xrp_price_aggregate/providers/binance.py
xrp_price_aggregate/providers/bitrue.py
xrp_price_aggregate/providers/bitstamp.py
xrp_price_aggregate/providers/gen_default.py
xrp_price_aggregate/providers/hitbtc.py
xrp_price_aggregate/providers/kraken.py
xrp_price_aggregate/providers/threexrp.py
xrp_price_aggregate/providers/xrpl_oracle.py
xrp_price_aggregate-0.0.15.dist-info/LICENSE
xrp_price_aggregate-0.0.15.dist-info/METADATA
xrp_price_aggregate-0.0.15.dist-info/WHEEL
xrp_price_aggregate-0.0.15.dist-info/top_level.txt
xrp_price_aggregate-0.0.15.dist-info/RECORD
