Metadata-Version: 2.1
Name: xrp-price-aggregate
Version: 0.0.15
Summary: A utility library that wraps grabbing the current spot price of $XRP from various exchanges.
Home-page: https://github.com/yyolk/xrp-price-aggregate
Author: Joseph Chiocchi
Author-email: joe@yolk.cc
License: UNKNOWN
Project-URL: Bug Tracker, https://github.com/yyolk/xrp-price-aggregate/issues
Project-URL: Source, https://github.com/yyolk/xrp-price-aggregate/
Keywords: xrp,xrpl,ccxt,cryptocurrency
Platform: UNKNOWN
Classifier: Intended Audience :: Developers
Classifier: License :: OSI Approved :: ISC License (ISCL)
Classifier: Programming Language :: Python :: 3
Classifier: Programming Language :: Python :: 3.7
Classifier: Programming Language :: Python :: 3.8
Classifier: Programming Language :: Python :: 3.9
Classifier: Programming Language :: Python :: 3.10
Classifier: Programming Language :: Python :: 3 :: Only
Requires-Python: <4,>=3.7
License-File: LICENSE
Requires-Dist: ccxt (~=1.54.45)
Requires-Dist: httpx (~=0.18.2)
Requires-Dist: websockets (~=9.1)
